oc_extras/__init__.py
oc_extras/resolvers.py
oc_extras/utils/__init__.py
oc_extras/utils/utils.py
oc_extras-0.3.1.dist-info/LICENSE
oc_extras-0.3.1.dist-info/METADATA
oc_extras-0.3.1.dist-info/WHEEL
oc_extras-0.3.1.dist-info/top_level.txt
oc_extras-0.3.1.dist-info/RECORD
